{
    "CS": {
        "CS 421": {
            "name": "Computer Networks",
            "sections": {
                "1": {
                    "schedule": [
                        "wed_0830",
                        "wed_0930",
                        "fri_1030",
                        "fri_1130"
                    ],
                    "gpa": 2.59
                },
                "2": {
                    "schedule": [
                        "thu_1330",
                        "thu_1430",
                        "mon_1530",
                        "mon_1630"
                    ],
                    "gpa": 2.27
                }
            },
            "gpa": 2.44
        }
    },
    "CTIS": {
        "CTIS 163": {
            "name": "Discrete Mathematics ",
            "sections": {
                "1": {
                    "schedule": [
                        "wed_0830",
                        "wed_0930",
                        "fri_1030",
                        "fri_1130"
                    ],
                    "gpa": 2.03
                }
            },
            "gpa": 2.03
        },
        "CTIS 164": {
            "name": "Technical Mathematics with Programming ",
            "sections": {
                "1": {
                    "schedule": [
                        "tue_1330",
                        "tue_1430",
                        "thu_1530",
                        "thu_1630"
                    ],
                    "gpa": 2.65
                },
                "2": {
                    "schedule": [
                        "fri_0830",
                        "fri_0930",
                        "tue_1030",
                        "tue_1130"
                    ],
                    "gpa": 2.43
                },
                "3": {
                    "schedule": [
                        "fri_1330",
                        "fri_1430",
                        "tue_1530",
                        "tue_1630"
                    ],
                    "gpa": 2.02
                }
            },
            "gpa": 2.41
        },
        "CTIS 261": {
            "name": "Computer Networks I",
            "sections": {
                "1": {
                    "schedule": [
                        "tue_1330",
                        "tue_1430",
                        "thu_1530",
                        "thu_1630"
                    ],
                    "gpa": 1.67
                },
                "2": {
                    "schedule": [
                        "thu_0830",
                        "thu_0930",
                        "mon_1030",
                        "mon_1130"
                    ],
                    "gpa": 2.12
                }
            },
            "gpa": 1.9
        },
        "CTIS 262": {
            "name": "Computer Networks II",
            "sections": {
                "1": {
                    "schedule": [
                        "tue_0830",
                        "tue_0930",
                        "thu_1030",
                        "thu_1130"
                    ],
                    "gpa": 2.12
                },
                "2": {
                    "schedule": [
                        "tue_1330",
                        "tue_1430",
                        "thu_1530",
                        "thu_1630"
                    ],
                    "gpa": 1.78
                }
            },
            "gpa": 1.96
        },
        "CTIS 484": {
            "name": "Advanced Topics in Programming ",
            "sections": {
                "1": {
                    "schedule": [
                        "fri_0830",
                        "fri_0930",
                        "tue_1030",
                        "tue_1130"
                    ],
                    "gpa": 2.45
                },
                "2": {
                    "schedule": [
                        "tue_0830",
                        "tue_0930",
                        "thu_1030",
                        "thu_1130"
                    ],
                    "gpa": 2.04
                }
            },
            "gpa": 2.24
        },
        "CTIS 485": {
            "name": "Information Storage and Management",
            "sections": {
                "1": {
                    "schedule": [
                        "mon_1330",
                        "mon_1430",
                        "wed_1530",
                        "wed_1630"
                    ],
                    "gpa": 1.87
                },
                "2": {
                    "schedule": [
                        "thu_1330",
                        "thu_1430",
                        "mon_1530",
                        "mon_1630"
                    ],
                    "gpa": 2.19
                }
            },
            "gpa": 2
        }
    },
    "ECON": {
        "ECON 103": {
            "name": "Principles of Economics",
            "sections": {
                "1": {
                    "schedule": [
                        "tue_0830",
                        "tue_0930",
                        "thu_1030",
                        "thu_1130"
                    ],
                    "gpa": 2.27
                },
                "2": {
                    "schedule": [
                        "tue_1330",
                        "tue_1430",
                        "thu_1530",
                        "thu_1630"
                    ],
                    "gpa": 2.09
                },
                "3": {
                    "schedule": [
                        "wed_1330",
                        "wed_1430",
                        "fri_1530",
                        "fri_1630"
                    ],
                    "gpa": 2.26
                },
                "4": {
                    "schedule": [
                        "thu_1330",
                        "thu_1430",
                        "mon_1530",
                        "mon_1630"
                    ],
                    "gpa": 2.33
                },
                "5": {
                    "schedule": [
                        "wed_1330",
                        "wed_1430",
                        "fri_1530",
                        "fri_1630"
                    ],
                    "gpa": 1.09
                },
                "6": {
                    "schedule": [
                        "tue_1330",
                        "tue_1430",
                        "thu_1530",
                        "thu_1630"
                    ],
                    "gpa": 1.46
                }
            },
            "gpa": 1.89
        },
        "ECON 504": {
            "name": "Microeconomic Theory II",
            "sections": {
                "1": {
                    "schedule": [
                        "fri_0830",
                        "fri_0930",
                        "tue_1030",
                        "tue_1130"
                    ],
                    "gpa": 3.03
                }
            },
            "gpa": 3.03
        },
        "ECON 509": {
            "name": "Probability and Statistics I",
            "sections": {
                "1": {
                    "schedule": [
                        "tue_0830",
                        "tue_0930",
                        "thu_1030",
                        "thu_1130"
                    ],
                    "gpa": 2.84
                }
            },
            "gpa": 2.84
        },
        "ECON 510": {
            "name": "Probability and Statistics II",
            "sections": {
                "1": {
                    "schedule": [
                        "mon_0830",
                        "mon_0930",
                        "wed_1030",
                        "wed_1130"
                    ],
                    "gpa": 2.47
                }
            },
            "gpa": 2.47
        }
    },
    "LAW": {
        "LAW 104": {
            "name": "Constitutional Law II",
            "sections": {
                "1": {
                    "schedule": [
                        "mon_1330",
                        "mon_1430",
                        "wed_1530",
                        "wed_1630"
                    ],
                    "gpa": 2.75
                },
                "2": {
                    "schedule": [
                        "tue_1330",
                        "tue_1430",
                        "thu_1530",
                        "thu_1630"
                    ],
                    "gpa": 2.59
                },
                "3": {
                    "schedule": [
                        "mon_0830",
                        "mon_0930",
                        "wed_1030",
                        "wed_1130"
                    ],
                    "gpa": 3.22
                },
                "4": {
                    "schedule": [
                        "thu_0830",
                        "thu_0930",
                        "mon_1030",
                        "mon_1130"
                    ],
                    "gpa": 3.07
                }
            },
            "gpa": 2.81
        },
        "LAW 105": {
            "name": "Civil Law I",
            "sections": {
                "1": {
                    "schedule": [
                        "mon_0830",
                        "mon_0930",
                        "wed_1030",
                        "wed_1130"
                    ],
                    "gpa": 1.6
                }
            },
            "gpa": 1.6
        },
        "LAW 106": {
            "name": "Civil Law II",
            "sections": {
                "1": {
                    "schedule": [
                        "thu_0830",
                        "thu_0930",
                        "mon_1030",
                        "mon_1130"
                    ],
                    "gpa": 3.56
                },
                "2": {
                    "schedule": [
                        "tue_1330",
                        "tue_1430",
                        "thu_1530",
                        "thu_1630"
                    ],
                    "gpa": 2.79
                },
                "3": {
                    "schedule": [
                        "wed_0830",
                        "wed_0930",
                        "fri_1030",
                        "fri_1130"
                    ],
                    "gpa": 3.39
                },
                "4": {
                    "schedule": [
                        "wed_1330",
                        "wed_1430",
                        "fri_1530",
                        "fri_1630"
                    ],
                    "gpa": 3.35
                }
            },
            "gpa": 3.22
        },
        "LAW 201": {
            "name": "Law of Obligations I",
            "sections": {
                "1": {
                    "schedule": [
                        "thu_1330",
                        "thu_1430",
                        "mon_1530",
                        "mon_1630"
                    ],
                    "gpa": 2.56
                }
            },
            "gpa": 2.56
        },
        "LAW 202": {
            "name": "Law of Obligations II",
            "sections": {
                "1": {
                    "schedule": [
                        "tue_0830",
                        "tue_0930",
                        "thu_1030",
                        "thu_1130"
                    ],
                    "gpa": 2.21
                },
                "2": {
                    "schedule": [
                        "thu_1330",
                        "thu_1430",
                        "mon_1530",
                        "mon_1630"
                    ],
                    "gpa": 2.44
                },
                "3": {
                    "schedule": [
                        "tue_1330",
                        "tue_1430",
                        "thu_1530",
                        "thu_1630"
                    ],
                    "gpa": 2.56
                }
            },
            "gpa": 2.43
        },
        "LAW 204": {
            "name": "Criminal Law II",
            "sections": {
                "1": {
                    "schedule": [
                        "fri_1330",
                        "fri_1430",
                        "tue_1530",
                        "tue_1630"
                    ],
                    "gpa": 1.48
                },
                "2": {
                    "schedule": [
                        "mon_0830",
                        "mon_0930",
                        "wed_1030",
                        "wed_1130"
                    ],
                    "gpa": 2.71
                },
                "3": {
                    "schedule": [
                        "mon_1330",
                        "mon_1430",
                        "wed_1530",
                        "wed_1630"
                    ],
                    "gpa": 2.79
                },
                "4": {
                    "schedule": [
                        "fri_0830",
                        "fri_0930",
                        "tue_1030",
                        "tue_1130"
                    ],
                    "gpa": 2.32
                }
            },
            "gpa": 2.37
        },
        "LAW 206": {
            "name": "Administrative Law II",
            "sections": {
                "1": {
                    "schedule": [
                        "mon_1330",
                        "mon_1430",
                        "wed_1530",
                        "wed_1630"
                    ],
                    "gpa": 2.69
                },
                "2": {
                    "schedule": [
                        "mon_1330",
                        "mon_1430",
                        "wed_1530",
                        "wed_1630"
                    ],
                    "gpa": 2.78
                },
                "3": {
                    "schedule": [
                        "tue_0830",
                        "tue_0930",
                        "thu_1030",
                        "thu_1130"
                    ],
                    "gpa": 2.42
                },
                "4": {
                    "schedule": [
                        "tue_1330",
                        "tue_1430",
                        "thu_1530",
                        "thu_1630"
                    ],
                    "gpa": 2.77
                }
            },
            "gpa": 2.66
        },
        "LAW 216": {
            "name": "Introduction to Anglo-American Law",
            "sections": {
                "1": {
                    "schedule": [
                        "wed_0830",
                        "wed_0930",
                        "fri_1030",
                        "fri_1130"
                    ],
                    "gpa": 2.09
                },
                "2": {
                    "schedule": [
                        "wed_1330",
                        "wed_1430",
                        "fri_1530",
                        "fri_1630"
                    ],
                    "gpa": 2.25
                }
            },
            "gpa": 2.15
        },
        "LAW 302": {
            "name": "Civil Procedure II",
            "sections": {
                "1": {
                    "schedule": [
                        "thu_1330",
                        "thu_1430",
                        "mon_1530",
                        "mon_1630"
                    ],
                    "gpa": 2.48
                },
                "2": {
                    "schedule": [
                        "wed_1330",
                        "wed_1430",
                        "fri_1530",
                        "fri_1630"
                    ],
                    "gpa": 2.54
                }
            },
            "gpa": 2.5
        },
        "LAW 304": {
            "name": "Private International Law",
            "sections": {
                "1": {
                    "schedule": [
                        "tue_1330",
                        "tue_1430",
                        "thu_1530",
                        "thu_1630"
                    ],
                    "gpa": 2.87
                },
                "2": {
                    "schedule": [
                        "wed_1330",
                        "wed_1430",
                        "fri_1530",
                        "fri_1630"
                    ],
                    "gpa": 3.09
                },
                "3": {
                    "schedule": [
                        "wed_0830",
                        "wed_0930",
                        "fri_1030",
                        "fri_1130"
                    ],
                    "gpa": 3.22
                },
                "4": {
                    "schedule": [
                        "fri_0830",
                        "fri_0930",
                        "tue_1030",
                        "tue_1130"
                    ],
                    "gpa": 2.73
                }
            },
            "gpa": 2.97
        },
        "LAW 305": {
            "name": "Civil Law III: Law of Property I",
            "sections": {
                "1": {
                    "schedule": [
                        "wed_1330",
                        "wed_1430",
                        "fri_1530",
                        "fri_1630"
                    ],
                    "gpa": 2.03
                }
            },
            "gpa": 2.03
        },
        "LAW 306": {
            "name": "Civil Law III: Law of Property II",
            "sections": {
                "1": {
                    "schedule": [
                        "mon_1330",
                        "mon_1430",
                        "wed_1530",
                        "wed_1630"
                    ],
                    "gpa": 2.22
                },
                "2": {
                    "schedule": [
                        "thu_0830",
                        "thu_0930",
                        "mon_1030",
                        "mon_1130"
                    ],
                    "gpa": 2.32
                },
                "3": {
                    "schedule": [
                        "thu_1330",
                        "thu_1430",
                        "mon_1530",
                        "mon_1630"
                    ],
                    "gpa": 2.01
                },
                "4": {
                    "schedule": [
                        "wed_0830",
                        "wed_0930",
                        "fri_1030",
                        "fri_1130"
                    ],
                    "gpa": 2.21
                }
            },
            "gpa": 2.19
        },
        "LAW 307": {
            "name": "Commercial Law I",
            "sections": {
                "1": {
                    "schedule": [
                        "tue_1330",
                        "tue_1430",
                        "thu_1530",
                        "thu_1630"
                    ],
                    "gpa": 2.29
                }
            },
            "gpa": 2.29
        },
        "LAW 308": {
            "name": "Commercial Law II",
            "sections": {
                "1": {
                    "schedule": [
                        "thu_0830",
                        "thu_0930",
                        "mon_1030",
                        "mon_1130"
                    ],
                    "gpa": 2.07
                },
                "2": {
                    "schedule": [
                        "mon_0830",
                        "mon_0930",
                        "wed_1030",
                        "wed_1130"
                    ],
                    "gpa": 2.3
                },
                "3": {
                    "schedule": [
                        "tue_0830",
                        "tue_0930",
                        "thu_1030",
                        "thu_1130"
                    ],
                    "gpa": 2.65
                }
            },
            "gpa": 2.35
        },
        "LAW 401": {
            "name": "Commercial Law III",
            "sections": {
                "1": {
                    "schedule": [
                        "thu_1330",
                        "thu_1430",
                        "mon_1530",
                        "mon_1630"
                    ],
                    "gpa": 3.2
                }
            },
            "gpa": 3.2
        },
        "LAW 410": {
            "name": "Enforcement and Bankruptcy Law",
            "sections": {
                "1": {
                    "schedule": [
                        "thu_1030",
                        "fri_1030",
                        "thu_1130",
                        "fri_1130"
                    ],
                    "gpa": 2.77
                },
                "2": {
                    "schedule": [
                        "wed_1330",
                        "wed_1430",
                        "fri_1530",
                        "fri_1630"
                    ],
                    "gpa": 2.46
                }
            },
            "gpa": 2.74
        },
        "LAW 411": {
            "name": "Criminal Procedure ",
            "sections": {
                "1": {
                    "schedule": [
                        "tue_1330",
                        "tue_1430",
                        "thu_1530",
                        "thu_1630"
                    ],
                    "gpa": 2.79
                }
            },
            "gpa": 2.79
        }
    },
    "MATH": {
        "MATH 101": {
            "name": "Calculus I",
            "sections": {
                "1": {
                    "schedule": [
                        "wed_0830",
                        "wed_0930",
                        "fri_1030",
                        "fri_1130"
                    ],
                    "gpa": 1.71
                },
                "2": {
                    "schedule": [
                        "thu_0830",
                        "thu_0930",
                        "mon_1030",
                        "mon_1130"
                    ],
                    "gpa": 2.41
                },
                "3": {
                    "schedule": [
                        "fri_1330",
                        "fri_1430",
                        "tue_1530",
                        "tue_1630"
                    ],
                    "gpa": 1.88
                },
                "4": {
                    "schedule": [
                        "mon_0830",
                        "mon_0930",
                        "wed_1030",
                        "wed_1130"
                    ],
                    "gpa": 1.74
                },
                "5": {
                    "schedule": [
                        "tue_0830",
                        "tue_0930",
                        "thu_1030",
                        "thu_1130"
                    ],
                    "gpa": 1.28
                },
                "6": {
                    "schedule": [
                        "tue_0830",
                        "tue_0930",
                        "thu_1030",
                        "thu_1130"
                    ],
                    "gpa": 1.39
                },
                "7": {
                    "schedule": [
                        "tue_0830",
                        "tue_0930",
                        "thu_1030",
                        "thu_1130"
                    ],
                    "gpa": 1.6
                }
            },
            "gpa": 1.79
        },
        "MATH 102": {
            "name": "Calculus II",
            "sections": {
                "1": {
                    "schedule": [
                        "wed_0830",
                        "wed_0930",
                        "fri_1030",
                        "fri_1130"
                    ],
                    "gpa": 1.87
                },
                "2": {
                    "schedule": [
                        "thu_0830",
                        "thu_0930",
                        "mon_1030",
                        "mon_1130"
                    ],
                    "gpa": 2.76
                },
                "3": {
                    "schedule": [
                        "fri_1330",
                        "fri_1430",
                        "tue_1530",
                        "tue_1630"
                    ],
                    "gpa": 1.09
                },
                "4": {
                    "schedule": [
                        "wed_1330",
                        "wed_1430",
                        "fri_1530",
                        "fri_1630"
                    ],
                    "gpa": 1.7
                },
                "5": {
                    "schedule": [
                        "wed_1330",
                        "wed_1430",
                        "fri_1530",
                        "fri_1630"
                    ],
                    "gpa": 1.89
                },
                "6": {
                    "schedule": [
                        "thu_0830",
                        "thu_0930",
                        "mon_1030",
                        "mon_1130"
                    ],
                    "gpa": 2.33
                },
                "7": {
                    "schedule": [
                        "fri_0830",
                        "fri_0930",
                        "tue_1030",
                        "tue_1130"
                    ],
                    "gpa": 2.13
                },
                "8": {
                    "schedule": [
                        "mon_0830",
                        "mon_0930",
                        "wed_1030",
                        "wed_1130"
                    ],
                    "gpa": 1.56
                },
                "9": {
                    "schedule": [
                        "tue_0830",
                        "tue_0930",
                        "thu_1030",
                        "thu_1130"
                    ],
                    "gpa": 1.85
                },
                "10": {
                    "schedule": [
                        "wed_0830",
                        "wed_0930",
                        "fri_1030",
                        "fri_1130"
                    ],
                    "gpa": 1.91
                },
                "11": {
                    "schedule": [
                        "mon_0830",
                        "mon_0930",
                        "wed_1030",
                        "wed_1130"
                    ],
                    "gpa": 2.07
                },
                "12": {
                    "schedule": [
                        "tue_1330",
                        "tue_1430",
                        "thu_1530",
                        "thu_1630"
                    ],
                    "gpa": 2.33
                },
                "13": {
                    "schedule": [
                        "wed_0830",
                        "wed_0930",
                        "fri_1030",
                        "fri_1130"
                    ],
                    "gpa": 1.55
                },
                "14": {
                    "schedule": [
                        "mon_0830",
                        "mon_0930",
                        "wed_1030",
                        "wed_1130"
                    ],
                    "gpa": 1.29
                },
                "15": {
                    "schedule": [
                        "tue_1330",
                        "tue_1430",
                        "thu_1530",
                        "thu_1630"
                    ],
                    "gpa": 0.93
                },
                "16": {
                    "schedule": [
                        "tue_0830",
                        "tue_0930",
                        "thu_1030",
                        "thu_1130"
                    ],
                    "gpa": 1.63
                }
            },
            "gpa": 1.92
        },
        "MATH 105": {
            "name": "Introduction to Calculus I",
            "sections": {
                "1": {
                    "schedule": [
                        "tue_1330",
                        "tue_1430",
                        "thu_1530",
                        "thu_1630"
                    ],
                    "gpa": 2.49
                },
                "2": {
                    "schedule": [
                        "mon_1330",
                        "mon_1430",
                        "wed_1530",
                        "wed_1630"
                    ],
                    "gpa": 2.38
                },
                "3": {
                    "schedule": [
                        "mon_0830",
                        "mon_0930",
                        "wed_1030",
                        "wed_1130"
                    ],
                    "gpa": 2.63
                },
                "4": {
                    "schedule": [
                        "wed_1330",
                        "wed_1430",
                        "fri_1530",
                        "fri_1630"
                    ],
                    "gpa": 1.99
                }
            },
            "gpa": 2.37
        },
        "MATH 106": {
            "name": "Introduction to Calculus II",
            "sections": {
                "1": {
                    "schedule": [
                        "tue_1330",
                        "tue_1430",
                        "thu_1530",
                        "thu_1630"
                    ],
                    "gpa": 2.25
                },
                "2": {
                    "schedule": [
                        "mon_1330",
                        "mon_1430",
                        "wed_1530",
                        "wed_1630"
                    ],
                    "gpa": 2.1
                },
                "3": {
                    "schedule": [
                        "thu_0830",
                        "thu_0930",
                        "mon_1030",
                        "mon_1130"
                    ],
                    "gpa": 2.05
                },
                "4": {
                    "schedule": [
                        "fri_0830",
                        "fri_0930",
                        "tue_1030",
                        "tue_1130"
                    ],
                    "gpa": 2.14
                },
                "6": {
                    "schedule": [
                        "thu_0830",
                        "thu_0930",
                        "mon_1030",
                        "mon_1130"
                    ],
                    "gpa": 2.01
                }
            },
            "gpa": 2.12
        },
        "MATH 124": {
            "name": "Abstract Mathematics II",
            "sections": {
                "1": {
                    "schedule": [
                        "wed_0830",
                        "wed_0930",
                        "fri_1030",
                        "fri_1130"
                    ],
                    "gpa": 1.22
                }
            },
            "gpa": 1.22
        },
        "MATH 225": {
            "name": "Linear Algebra and Differential Equations",
            "sections": {
                "1": {
                    "schedule": [
                        "fri_1330",
                        "fri_1430",
                        "tue_1530",
                        "tue_1630"
                    ],
                    "gpa": 2.52
                },
                "2": {
                    "schedule": [
                        "thu_0830",
                        "thu_0930",
                        "mon_1030",
                        "mon_1130"
                    ],
                    "gpa": 1.65
                },
                "3": {
                    "schedule": [
                        "thu_1330",
                        "thu_1430",
                        "mon_1530",
                        "mon_1630"
                    ],
                    "gpa": 2.11
                },
                "4": {
                    "schedule": [
                        "wed_0830",
                        "wed_0930",
                        "fri_1030",
                        "fri_1130"
                    ],
                    "gpa": 2.16
                },
                "5": {
                    "schedule": [
                        "fri_0830",
                        "fri_0930",
                        "tue_1030",
                        "tue_1130"
                    ],
                    "gpa": 1.84
                }
            },
            "gpa": 2.1
        },
        "MATH 241": {
            "name": "Engineering Mathematics I",
            "sections": {
                "1": {
                    "schedule": [
                        "fri_1330",
                        "fri_1430",
                        "tue_1530",
                        "tue_1630"
                    ],
                    "gpa": 2.59
                },
                "2": {
                    "schedule": [
                        "wed_0830",
                        "wed_0930",
                        "fri_1030",
                        "fri_1130"
                    ],
                    "gpa": 2.54
                }
            },
            "gpa": 2.57
        },
        "MATH 242": {
            "name": "Engineering Mathematics II",
            "sections": {
                "1": {
                    "schedule": [
                        "fri_1330",
                        "fri_1430",
                        "tue_1530",
                        "tue_1630"
                    ],
                    "gpa": 2.73
                },
                "2": {
                    "schedule": [
                        "wed_0830",
                        "wed_0930",
                        "fri_1030",
                        "fri_1130"
                    ],
                    "gpa": 2.26
                },
                "3": {
                    "schedule": [
                        "mon_1330",
                        "mon_1430",
                        "wed_1530",
                        "wed_1630"
                    ],
                    "gpa": 2.44
                }
            },
            "gpa": 2.52
        },
        "MATH 255": {
            "name": "Probability and Statistics",
            "sections": {
                "1": {
                    "schedule": [
                        "mon_1330",
                        "mon_1430",
                        "wed_1530",
                        "wed_1630"
                    ],
                    "gpa": 2.5
                },
                "2": {
                    "schedule": [
                        "thu_1330",
                        "thu_1430",
                        "mon_1530",
                        "mon_1630"
                    ],
                    "gpa": 2.64
                }
            },
            "gpa": 2.56
        }
    }
}